price_parser/__init__.py
price_parser/constants.py
price_parser/parser.py
price_parser/type_price.py
price_parser_reworkd-0.3.0.dist-info/LICENSE.txt
price_parser_reworkd-0.3.0.dist-info/METADATA
price_parser_reworkd-0.3.0.dist-info/WHEEL
price_parser_reworkd-0.3.0.dist-info/top_level.txt
price_parser_reworkd-0.3.0.dist-info/RECORD
