Metadata-Version: 2.1
Name: price-parser-reworkd
Version: 0.3.0
Summary: A simple price parser for extracting currency and value from strings (currently used as a Pydantic datatype only).
Home-page: https://github.com/mohamedmamdouh22/price-parser.git
Author: Mohamed Khalil
Author-email: mkhalil@reworkd.ai
Classifier: Programming Language :: Python :: 3
Classifier: License :: OSI Approved :: MIT License
Classifier: Operating System :: OS Independent
Requires-Python: >=3.6
License-File: LICENSE.txt
Requires-Dist: pydantic
Requires-Dist: pytest
